config/__init__.py
config/_helpers.py
config/config.py
config/enums.py
config/envconfig.py
config/exceptions.py
config/interface.py
config/py.typed
config/utils.py
env_star-2.6.0.dist-info/LICENSE
env_star-2.6.0.dist-info/METADATA
env_star-2.6.0.dist-info/WHEEL
env_star-2.6.0.dist-info/RECORD
