Metadata-Version: 2.3
Name: env-star
Version: 2.6.0
Summary: a minimalist config manager
Home-page: https://github.com/gustcorrea/env-vars
License: MIT
Author: Gustavo Correa
Author-email: self.gustavocardoso@gmail.com
Requires-Python: >=3.10,<4.0
Classifier: License :: OSI Approved :: MIT License
Classifier: Programming Language :: Python :: 3
Classifier: Programming Language :: Python :: 3.10
Classifier: Programming Language :: Python :: 3.11
Classifier: Programming Language :: Python :: 3.12
Classifier: Programming Language :: Python :: 3.13
Classifier: Programming Language :: Python :: 3 :: Only
Classifier: Programming Language :: Python :: 3.9
Requires-Dist: gyver-attrs (>=0.9.4,<0.10.0)
Requires-Dist: lazy-fields (>=1.0.1,<2.0.0)
Requires-Dist: typing-extensions (>=4.7.1,<5.0.0)
Project-URL: Repository, https://github.com/gustcorrea/env-vars
